[
{
  "model": "cinema.reservation",
  "pk": 1,
  "fields": {
    "created": "2024-09-14T20:17:00.120Z",
    "user": 2,
    "seance": 4,
    "paid": false,
    "uuid": "9a2966d51caa5a6b58b8344cd0af0fd9",
    "used": false,
    "cancelled": false
  }
},
{
  "model": "cinema.reservation",
  "pk": 2,
  "fields": {
    "created": "2024-09-14T22:17:17.712Z",
    "user": 2,
    "seance": 4,
    "paid": false,
    "uuid": "60b021fd45c297c6a9162f80b40b5ea2",
    "used": false,
    "cancelled": false
  }
},
{
  "model": "cinema.reservation",
  "pk": 3,
  "fields": {
    "created": "2024-09-14T22:18:36.782Z",
    "user": 2,
    "seance": 4,
    "paid": false,
    "uuid": "8d3fcaad5956aa23bf585726eec7655b",
    "used": false,
    "cancelled": false
  }
},
{
  "model": "cinema.reservation",
  "pk": 4,
  "fields": {
    "created": "2024-09-14T22:32:54.622Z",
    "user": 2,
    "seance": 4,
    "paid": false,
    "uuid": "9af0b7c9c0243fbe84a9cf7eb93fba67",
    "used": false,
    "cancelled": false
  }
},
{
  "model": "cinema.reservation",
  "pk": 5,
  "fields": {
    "created": "2024-09-29T13:42:56.389Z",
    "user": 2,
    "seance": 20,
    "paid": false,
    "uuid": "498273b28affc201dbeccabf38b89f1a",
    "used": false,
    "cancelled": false
  }
},
{
  "model": "cinema.reservation",
  "pk": 6,
  "fields": {
    "created": "2024-09-29T13:42:57.258Z",
    "user": 2,
    "seance": 21,
    "paid": false,
    "uuid": "994a6f14c4fc3cac133c03ee47283421",
    "used": false,
    "cancelled": false
  }
},
{
  "model": "cinema.reservation",
  "pk": 7,
  "fields": {
    "created": "2024-09-29T13:42:57.903Z",
    "user": 2,
    "seance": 22,
    "paid": false,
    "uuid": "8f03c03e40b6ab0bb29bad06acd66e6d",
    "used": false,
    "cancelled": false
  }
},
{
  "model": "cinema.reservation",
  "pk": 8,
  "fields": {
    "created": "2024-09-29T13:42:58.638Z",
    "user": 2,
    "seance": 23,
    "paid": false,
    "uuid": "2c3be09b940dddace9c940046f08653e",
    "used": false,
    "cancelled": false
  }
},
{
  "model": "cinema.reservation",
  "pk": 9,
  "fields": {
    "created": "2024-09-29T13:42:58.992Z",
    "user": 2,
    "seance": 24,
    "paid": false,
    "uuid": "ee2b43a95c0909383854001dc85220d6",
    "used": false,
    "cancelled": false
  }
},
{
  "model": "cinema.reservation",
  "pk": 10,
  "fields": {
    "created": "2024-09-29T13:42:59.447Z",
    "user": 2,
    "seance": 25,
    "paid": false,
    "uuid": "5b7152a3c3e75659628181c194b1bced",
    "used": false,
    "cancelled": false
  }
},
{
  "model": "cinema.reservation",
  "pk": 12,
  "fields": {
    "created": "2024-09-29T13:43:00.175Z",
    "user": 2,
    "seance": 27,
    "paid": false,
    "uuid": "aa2d5c926911b7c30ff8f63c7c662024",
    "used": false,
    "cancelled": false
  }
},
{
  "model": "cinema.reservation",
  "pk": 13,
  "fields": {
    "created": "2024-09-29T13:43:00.899Z",
    "user": 2,
    "seance": 28,
    "paid": false,
    "uuid": "8eed50a9376faf3f5743470b9a6cb7a1",
    "used": false,
    "cancelled": false
  }
},
{
  "model": "cinema.reservation",
  "pk": 14,
  "fields": {
    "created": "2024-09-29T13:43:01.297Z",
    "user": 2,
    "seance": 29,
    "paid": false,
    "uuid": "1b76705c862b83c88623e36af33c38f2",
    "used": false,
    "cancelled": false
  }
}
]
